fastapi_sanitize-0.0.1.dist-info/licenses/LICENSE
fastapi_sanitizer/__init__.py
fastapi_sanitizer/middleware.py
fastapi_sanitizer/sanitizer.py
fastapi_sanitize-0.0.1.dist-info/METADATA
fastapi_sanitize-0.0.1.dist-info/WHEEL
fastapi_sanitize-0.0.1.dist-info/top_level.txt
fastapi_sanitize-0.0.1.dist-info/RECORD
