Metadata-Version: 2.4
Name: fastapi-sanitize
Version: 0.0.1
Summary: Configurable FastAPI middleware for input/output sanitization
License: MIT License
Classifier: Programming Language :: Python :: 3
Classifier: License :: OSI Approved :: MIT License
Classifier: Framework :: FastAPI
License-File: LICENSE
Requires-Dist: fastapi>=0.95
Requires-Dist: starlette>=0.20
Requires-Dist: bleach>=6.0
Dynamic: license-file
